{
  "$schema": "../node_modules/@tauri-apps/cli/schema.json",
  "package": {
    "productName": "solitude",
    "version": "0.2.0"
  },
  "build": {
    "distDir": "../dist",
    "devPath": "http://localhost:5173",
    "beforeDevCommand": "pnpm dev",
    "beforeBuildCommand": "pnpm build"
  },
  "tauri": {
    "bundle": {
      "active": true,
      "targets": "all",
      "identifier": "solitude.nat5uk1",
      "icon": [
        "../assets/logo.png",
        "./icons/icon.ico"
      ],
      "resources": [],
      "externalBin": [],
      "copyright": "",
      "category": "DeveloperTool",
      "shortDescription": "",
      "longDescription": "",
      "deb": {
        "depends": []
      },
      "macOS": {
        "frameworks": [],
        "minimumSystemVersion": "",
        "exceptionDomain": "",
        "signingIdentity": null,
        "providerShortName": null,
        "entitlements": null
      },
      "windows": {
        "certificateThumbprint": null,
        "digestAlgorithm": "sha256",
        "timestampUrl": ""
      }
    },
    "updater": {
      "active": false
    },
    "allowlist": {
      "all": true
    },
    "windows": [
      {
        "title": "Solitude - Artillery Mil Calculator For HLL",
        "width": 800,
        "height": 600,
        "resizable": true,
        "fullscreen": false,
        "alwaysOnTop": true
      }
    ],
    "security": {
      "csp": null
    },
    "macOSPrivateApi": true
  }
}